[
 { "cat": "prayerless", "field": "prayers", "match": "주님, 말씀의 깊이를 되찾게 하시옵소서. 게으름이 아닌 지혜를 주시옵소서", "new": "" },
 { "cat": "prayerless", "field": "prayers", "match": "주님, 말씀 속에서 깊은 통찰을 얻게 하소서. 게으름이 아닌 열정이 우리를 이끌게", "new": "" },
 { "cat": "prayerless", "field": "prayers", "match": "하나님 아버지, 기도하는 시간을 되찾게 하소서. 게으름이 아닌 진심이 말씀의 열매를", "new": "" },

 { "cat": "fear", "field": "prayers", "match": "제 마음을 당신의 계획으로 이끌어 주시고, 현재의 평온함 속에서 미래의 희망을 발견하게", "new": "" },
 { "cat": "fear", "field": "prayers", "match": "제 마음을 당신의 계획으로 이끌어주시고, 작은 일상에서 그분의 평화로운 메시지를 듣게", "new": "" },

 { "cat": "shame", "field": "prayers", "match": "제 안의 모든 수치와 자기혐오를 드러내시며, 진정한 자아를 보게 하옵소서", "new": "" },
 { "cat": "shame", "field": "prayers", "match": "제 안의 모든 부족함과 실패의 순간을 통해 제 잠재력을 발견하게", "new": "" },

 { "cat": "ingratitude", "field": "prayers", "match": "제 마음속의 원망이 사라지고, 모든 순간이 당신의 사랑과 지혜의 표현임을", "new": "" },
 { "cat": "ingratitude", "field": "prayers", "match": "오늘의 불편함 속에서도 당신의 지혜와 사랑을 깨닫게 하시고, 감사의 마음을 키워주소서", "new": "" },
 { "cat": "ingratitude", "field": "prayers", "match": "작은 불편함 속에서도 하나님의 지혜와 사랑을 찾게 하시고, 감사의 눈으로", "new": "" },

 { "cat": "doubt", "field": "prayers", "match": "어둠 속에서도 당신의 말씀을 듣게 하소서. 침체된 마음을 따뜻한 위로로 채우소서", "new": "" },
 { "cat": "doubt", "field": "prayers", "match": "침체된 마음을 위로하시고, 당신의 약속을 명확히 들려주시길 간구합니다", "new": "" },
 { "cat": "doubt", "field": "prayers", "match": "침체된 마음을 깨우시고 다시 활력을 불어넣어 주시기를 간구합니다", "new": "" },

 { "cat": "gossip", "field": "prayers", "match": "험담이 아닌 치유의 말로 대화하게 하소서. 제 입술이 언제나 상대방의 영혼을 회복", "new": "" },
 { "cat": "greed", "field": "prayers", "match": "제 마음 속에 잠들어 있는 불안과 탐욕을 아시고 고쳐주소서. 십자가의 은혜를 통해 얻은 자유", "new": "" },
 { "cat": "lie", "field": "prayers", "match": "제 안의 위선과 거짓을 인정하고 용서해 주시기를 구합니다. 예수님의 은혜로 다시 태어나게", "new": "" },
 { "cat": "sloth", "field": "prayers", "match": "게으름과 미루기가 나를 방해하지 않게 하소서. 회복과 소망의 마음으로", "new": "" },
 { "cat": "unforgive", "field": "prayers", "match": "제 마음의 벽을 깨뜨리시고 진실된 감정을 표현할 수 있는 용기를 주시옵소서", "new": "" }
]
